ET_Client.py
LICENSE
MANIFEST.in
README.md
config.python.template
requirements.txt
setup.py
FuelSDK/__init__.py
FuelSDK/client.py
FuelSDK/objects.py
FuelSDK/rest.py
FuelSDK/suds_patch.py
FuelSDK.egg-info/PKG-INFO
FuelSDK.egg-info/SOURCES.txt
FuelSDK.egg-info/dependency_links.txt
FuelSDK.egg-info/requires.txt
FuelSDK.egg-info/top_level.txt