Metadata-Version: 1.1
Name: FuelSDK
Version: 0.9.0
Summary: ExactTarget Fuel SDK for Python
Home-page: https://github.com/ExactTarget/FuelSDK-Python
Author: ExactTarget
Author-email: code@exacttarget.com
License: MIT
Platform: UNKNOWN
Classifier: Development Status :: 5 - Production/Stable
Classifier: Intended Audience :: Developers
Classifier: License :: OSI Approved :: MIT License
Classifier: Operating System :: OS Independent
Classifier: Topic :: Software Development :: Libraries
Classifier: Programming Language :: Python :: 2.7
